{
  "_meta": {
    "ai_asset_version": 9
  },
  "dimensions": {
    "agent": {
      "frozen_ts": "2026-06-07T20:12:39+00:00",
      "source": "agent_eval_results.json",
      "source_generated_ts": "2026-06-07T20:12:13+00:00",
      "tolerance_pp": 5.0,
      "locked_test": {
        "pass_rate": 100.0,
        "n": 2
      },
      "val": {
        "pass_rate": 100.0,
        "n": 4
      },
      "train": {
        "pass_rate": 100.0,
        "n": 13
      }
    },
    "rag": {
      "frozen_ts": "2026-06-24T04:34:23+00:00",
      "source": "rag_eval_results.json",
      "source_generated_ts": "2026-06-24T04:33:55+00:00",
      "tolerance_pp": 25.0,
      "locked_test": {
        "pass_rate": 100.0,
        "n": 4
      },
      "val": {
        "pass_rate": 85.7,
        "n": 7
      },
      "train": {
        "pass_rate": 84.2,
        "n": 19
      }
    },
    "memory": {
      "frozen_ts": "2026-06-24T02:41:30+00:00",
      "source": "memory_eval_results.json",
      "source_generated_ts": "2026-06-24T02:40:39+00:00",
      "tolerance_pp": 12.0,
      "locked_test": {
        "pass_rate": 77.8,
        "n": 9
      },
      "val": {
        "pass_rate": 92.3,
        "n": 13
      },
      "train": {
        "pass_rate": 92.6,
        "n": 27
      }
    },
    "persona": {
      "frozen_ts": "2026-06-24T04:14:09+00:00",
      "source": "persona_eval_results.json",
      "source_generated_ts": "2026-06-24T04:13:03+00:00",
      "tolerance_pp": 12.0,
      "locked_test": {
        "pass_rate": 90.0,
        "n": 10
      },
      "val": {
        "pass_rate": 100.0,
        "n": 4
      },
      "train": {
        "pass_rate": 88.2,
        "n": 17
      }
    },
    "domain": {
      "frozen_ts": "2026-06-09T13:17:03+00:00",
      "source": "domain_eval_results.json",
      "source_generated_ts": "2026-06-09T13:12:21+00:00",
      "tolerance_pp": 5.0,
      "locked_test": {
        "pass_rate": 100.0,
        "n": 1
      },
      "val": {
        "pass_rate": 100.0,
        "n": 2
      },
      "train": {
        "pass_rate": 33.3,
        "n": 3
      }
    },
    "robustness": {
      "frozen_ts": "2026-06-09T13:17:04+00:00",
      "source": "robustness_eval_results.json",
      "source_generated_ts": "2026-06-09T13:12:22+00:00",
      "tolerance_pp": 5.0,
      "locked_test": {
        "pass_rate": 50.0,
        "n": 2
      },
      "val": {
        "pass_rate": 100.0,
        "n": 2
      },
      "train": {
        "pass_rate": 33.3,
        "n": 3
      }
    }
  }
}