{
  "timestamp": "2026-05-22T07:16:03.752321",
  "passed": 5,
  "failed": 0,
  "results": [
    {
      "id": "coverage-map",
      "status": "PASS",
      "duration": 29.6,
      "stderr": ""
    },
    {
      "id": "gap-proposer",
      "status": "PASS",
      "duration": 0.6,
      "stderr": ""
    },
    {
      "id": "pattern-consistency",
      "status": "PASS",
      "duration": 0.3,
      "stderr": ""
    },
    {
      "id": "depth",
      "status": "PASS",
      "duration": 0.2,
      "stderr": ""
    },
    {
      "id": "freshness",
      "status": "PASS",
      "duration": 0.2,
      "stderr": ""
    }
  ]
}